{
  "name": "Chrome Extension Dev",
  "image": "mcr.microsoft.com/devcontainers/base:bullseye",
  "features": {
    "ghcr.io/devcontainers/features/git:1": {},
    "ghcr.io/devcontainers/features/github-cli:1": {},
    "ghcr.io/devcontainers/features/docker-outside-of-docker:1": {},
    "ghcr.io/devcontainers/features/node:1": {
      "version": "20"
    },
    "ghcr.io/devcontainers/features/java:1": {
      "version": "21",
      "jdkDistro": "ms"
    }
  },
  "customizations": {
    "vscode": {
      "settings": {
        "typescript.tsserver.experimental.enableProjectDiagnostics": true,
        "terminal.integrated.defaultProfile.linux": "bash",
        "workbench.colorTheme": "oh-lucy",
        "workbench.iconTheme": "material-icon-theme",
        "java.jdt.ls.java.home": "/usr/local/sdkman/candidates/java/current"
      },
      "extensions": [
        "dbaeumer.vscode-eslint",
        "esbenp.prettier-vscode",
        "ms-vscode.vscode-typescript-next",
        "eamodio.gitlens",
        "hermitter.oh-lucy-vscode",
        "pkief.material-icon-theme",
        "github.vscode-github-actions",
        "vmware.vscode-boot-dev-pack",
        "vscjava.vscode-java-pack"
      ]
    }
  },
  "updateContentCommand": "bash .devcontainer/setup.sh",
  "forwardPorts": [
    3000,
    4173,
    8080,
    5000,
    9292,
    7001
  ],
  "runArgs": [
    "--network=snippetquiz"
  ]
}